{
  "$schema": "http://json-schema.org/draft-07/schema#",
  "title": "QueryResponse",
  "anyOf": [
    {
      "type": "object",
      "required": [
        "get_rate"
      ],
      "properties": {
        "get_rate": {
          "type": "object",
          "required": [
            "rate"
          ],
          "properties": {
            "rate": {
              "$ref": "#/definitions/Uint128"
            }
          }
        }
      }
    }
  ],
  "definitions": {
    "Uint128": {
      "type": "string"
    }
  }
}
